[
  {
    "id": "651",
    "question": "Dans Bloodborne, quel est le nom du boss connu pour son apparence de loup-garou ?",
    "answer": "Vicaire Amelia",
    "badAnswers": [
      "Clerc Bestial",
      "Père Gascoigne",
      "Ludwig"
    ],
    "category": "Jeux vidéo",
    "difficulty": "normal",
    "description": "Le Vicaire Amelia est un boss de Bloodborne qui se transforme en une créature lupine géante dans la cathédrale. Le Clerc Bestial, Gascoigne et Ludwig sont d'autres boss, mais avec des caractéristiques différentes."
  },
  {
    "id": "581",
    "question": "Dans Dark Souls III, quel est le nom du royaume où se déroule l'histoire ?",
    "answer": "Lothric",
    "badAnswers": [
      "Lordran",
      "Drangleic",
      "Yharnam"
    ],
    "category": "Jeux vidéo",
    "difficulty": "normal",
    "description": "Dark Souls III se déroule dans le royaume de Lothric, où le joueur explore un monde en déclin pour rallumer la Première Flamme. Lordran et Drangleic sont dans Dark Souls et Dark Souls II, et Yharnam dans Bloodborne."
  },
  {
    "id": "2045",
    "question": "Quel est le nom de l'auteur de 'Le Marin de Gibraltar' ?",
    "answer": "Marguerite Duras",
    "badAnswers": [
      "Jean-Paul Sartre",
      "Albert Camus",
      "André Gide"
    ],
    "category": "Livres",
    "difficulty": "normal",
    "description": "Marguerite Duras a écrit 'Le Marin de Gibraltar' (1952), un roman sur la quête amoureuse et l'errance."
  },
  {
    "id": "1633",
    "question": "Quel est le nom du film qui a remporté l'Oscar du meilleur film en 1934 ?",
    "answer": "Cavalcade",
    "badAnswers": [
      "Lady for a Day",
      "Little Women",
      "The Private Life of Henry VIII"
    ],
    "category": "Cinéma",
    "difficulty": "normal",
    "description": "Cavalcade, réalisé par Frank Lloyd, a remporté l'Oscar du meilleur film en 1934, un drame historique sur la société anglaise."
  },
  {
    "id": "2089",
    "question": "Quel est le nom de l'auteur de 'Albertine disparue' ?",
    "answer": "Marcel Proust",
    "badAnswers": [
      "Émile Zola",
      "Gustave Flaubert",
      "Alain-Fournier"
    ],
    "category": "Livres",
    "difficulty": "normal",
    "description": "Marcel Proust a écrit 'Albertine disparue' (1925), le sixième volume de 'À la recherche du temps perdu'."
  },
  {
    "id": "1713",
    "question": "Dans quel jeu vidéo trouve-t-on le personnage Raichu ?",
    "answer": "Pokémon",
    "badAnswers": [
      "Super Mario",
      "The Legend of Zelda",
      "Kirby"
    ],
    "category": "Jeux vidéo",
    "difficulty": "facile",
    "description": "Raichu, Pokémon de type électrique, est l'évolution de Pikachu dans la série Pokémon, connu pour sa puissance électrique."
  },
  {
    "id": "1957",
    "question": "Quel est le nom de l'auteur de 'Le Mur' ?",
    "answer": "Jean-Paul Sartre",
    "badAnswers": [
      "Albert Camus",
      "André Gide",
      "Simone de Beauvoir"
    ],
    "category": "Livres",
    "difficulty": "normal",
    "description": "Jean-Paul Sartre a écrit 'Le Mur' (1939), un recueil de nouvelles existentialistes."
  },
  {
    "id": "1199",
    "question": "Quel est le nom de l'auteur de 'Les Fleurs du mal' ?",
    "answer": "Charles Baudelaire",
    "badAnswers": [
      "Paul Verlaine",
      "Arthur Rimbaud",
      "Stéphane Mallarmé"
    ],
    "category": "Livres",
    "difficulty": "normal",
    "description": "Charles Baudelaire a écrit 'Les Fleurs du mal' (1857), un recueil de poèmes symbolistes explorant la beauté, le vice et la modernité."
  },
  {
    "id": "190",
    "question": "Quelle activité est directement associée à la danse 'Pasodoble' ?",
    "answer": "La corrida",
    "badAnswers": [
      "Le carnaval",
      "La plage",
      "L'opéra"
    ],
    "category": "Danse",
    "difficulty": "normal",
    "description": "Le pasodoble, danse espagnole, s'inspire des mouvements du torero lors d'une corrida. Les autres propositions n'ont aucun lien avec cette danse."
  },
  {
    "id": "1793",
    "question": "Quel est la capitale du Soudan du Sud ?",
    "answer": "Djouba",
    "badAnswers": [
      "Wau",
      "Malakal",
      "Bor"
    ],
    "category": "Géographie",
    "difficulty": "normal",
    "description": "Djouba, capitale du Soudan du Sud, est une ville en développement située sur les rives du Nil blanc."
  }
]